[
    {
        "CurrencyIsoCode": "USD",
        "FormulaExpression": "FILTER(LIST(AppointmentType:ServiceAccount),'IsChecked = \"true\"')",
        "FormulaResultPath": "Filtered:SelectedServiceAccount",
        "FormulaSequence": 1,
        "GlobalKey": "746e137f-5c72-442b-a02c-d21e764ddc52",
        "IsDisabled": false,
        "IsLocked": false,
        "IsRequiredForUpsert": false,
        "IsUpsertKey": false,
        "MayEdit": true,
        "Name": "FilterServiceAccounts",
        "OmniDataTransformationId": {
            "Name": "FilterServiceAccounts",
            "VlocityDataPackType": "VlocityMatchingKeyObject",
            "VlocityMatchingRecordSourceKey": "OmniDataTransform/FilterServiceAccounts",
            "VlocityRecordSObjectType": "OmniDataTransform"
        },
        "OutputCreationSequence": 0,
        "OutputFieldName": "Formula",
        "OutputObjectName": "Formula",
        "VlocityDataPackType": "SObject",
        "VlocityRecordSObjectType": "OmniDataTransformItem"
    },
    {
        "CurrencyIsoCode": "USD",
        "GlobalKey": "4f618966-495f-402d-be1d-ab00f4e4cdfc",
        "InputFieldName": "Filtered:SelectedServiceAccount",
        "IsDisabled": false,
        "IsLocked": false,
        "IsRequiredForUpsert": false,
        "IsUpsertKey": false,
        "MayEdit": true,
        "Name": "FilterServiceAccounts",
        "OmniDataTransformationId": {
            "Name": "FilterServiceAccounts",
            "VlocityDataPackType": "VlocityMatchingKeyObject",
            "VlocityMatchingRecordSourceKey": "OmniDataTransform/FilterServiceAccounts",
            "VlocityRecordSObjectType": "OmniDataTransform"
        },
        "OutputCreationSequence": 1,
        "OutputFieldName": "SelectedServiceAccount",
        "OutputObjectName": "json",
        "VlocityDataPackType": "SObject",
        "VlocityRecordSObjectType": "OmniDataTransformItem"
    }
]