{
    "CurrencyIsoCode": "USD",
    "IsActive": true,
    "IsLocked": false,
    "IsOmniScriptEmbeddable": false,
    "MayEdit": true,
    "Name": "NavigateAction",
    "OmniProcessId": {
        "Name": "Work Order Estimation",
        "VlocityDataPackType": "VlocityMatchingKeyObject",
        "VlocityMatchingRecordSourceKey": "OmniProcess/Demo/WorkOrderEstimationDCT/English",
        "VlocityRecordSObjectType": "OmniProcess"
    },
    "PropertySetConfig": {
        "HTMLTemplateId": "",
        "businessCategory": "",
        "businessEvent": "",
        "conditionType": "Hide if False",
        "controlWidth": 6,
        "iconName": "",
        "iconPosition": "left",
        "iconVariant": "",
        "label": "Navigate to Work Order",
        "loginAction": "login",
        "message": {
        },
        "objectAction": "home",
        "pubsub": false,
        "recordAction": "view",
        "replace": true,
        "show": null,
        "ssm": false,
        "targetFilter": "Recent",
        "targetId": "%accountId%",
        "targetLWCLayout": "lightning",
        "targetName": "Account",
        "targetParams": "",
        "targetType": "Record",
        "validationRequired": "Submit",
        "variant": "brand",
        "wpm": false
    },
    "Type": "Navigate Action",
    "VlocityDataPackType": "SObject",
    "VlocityRecordSObjectType": "OmniProcessElement",
    "VlocityRecordSourceKey": "OmniProcessElement/OmniProcess/Demo/WorkOrderEstimationDCT/English/NavigateAction"
}