{
    "CurrencyIsoCode": "USD",
    "DecisionMatrixType": "DecisionTable",
    "Description": "03/05: Debarshi",
    "GroupKey": "",
    "IsLocked": false,
    "MayEdit": true,
    "Name": "ProductQualificationDT",
    "Namespace": "",
    "SubGroupKey": "",
    "Type": "",
    "UniqueName": "ProductQualificationDT",
    "UsageType": "ProductQualification",
    "VlocityDataPackType": "SObject",
    "VlocityRecordSObjectType": "CalculationMatrix",
    "VlocityRecordSourceKey": "CalculationMatrix/ProductQualificationDT"
}