{
    "CurrencyIsoCode": "USD",
    "IsActive": true,
    "IsLocked": false,
    "IsOmniScriptEmbeddable": false,
    "MayEdit": true,
    "Name": "DRServicePointList",
    "OmniProcessId": {
        "Name": "Move Out",
        "VlocityDataPackType": "VlocityMatchingKeyObject",
        "VlocityMatchingRecordSourceKey": "OmniProcess/vplEnergy/MoveOut/English",
        "VlocityRecordSObjectType": "OmniProcess"
    },
    "PropertySetConfig": {
        "HTMLTemplateId": "",
        "bundle": "VPLGetServicePointAssetDetail",
        "controlWidth": 12,
        "dataRaptor Input Parameters": [
            {
                "element": "PremiseListDetail:PremiseListLWC:PremiseId",
                "inputParam": "PremiseId"
            },
            {
                "element": "AccountId",
                "inputParam": "BusinessAccountid"
            }
        ],
        "disOnTplt": false,
        "enableActionMessage": false,
        "enableDefaultAbort": false,
        "errorMessage": {
            "custom": [
            ],
            "default": null
        },
        "failureAbortLabel": "Abort",
        "failureAbortMessage": "Are you sure?",
        "failureGoBackLabel": "Go Back",
        "failureNextLabel": "Continue",
        "inProgressMessage": "In Progress",
        "label": "DRServicePointList",
        "message": {
        },
        "postMessage": "Done",
        "pubsub": false,
        "redirectNextLabel": "Next",
        "redirectNextWidth": 3,
        "redirectPageName": "",
        "redirectPreviousLabel": "Previous",
        "redirectPreviousWidth": 3,
        "redirectTemplateUrl": "vlcAcknowledge.html",
        "remoteTimeout": 30000,
        "responseJSONNode": "",
        "responseJSONPath": "",
        "show": null,
        "showPersistentComponent": [
            false,
            false
        ],
        "ssm": false,
        "validationRequired": "Step",
        "wpm": false
    },
    "Type": "DataRaptor Extract Action",
    "VlocityDataPackType": "SObject",
    "VlocityRecordSObjectType": "OmniProcessElement",
    "VlocityRecordSourceKey": "OmniProcessElement/OmniProcess/vplEnergy/MoveOut/English/DRServicePointList"
}