{
    "CurrencyIsoCode": "USD",
    "IsActive": true,
    "IsLocked": false,
    "IsOmniScriptEmbeddable": false,
    "MayEdit": true,
    "Name": "GetLineItems",
    "OmniProcessId": {
        "Name": "VPL Manage Billing Dispute 13-4 Lightning Ready",
        "VlocityDataPackType": "VlocityMatchingKeyObject",
        "VlocityMatchingRecordSourceKey": "OmniProcess/Service/BillingDispute/English",
        "VlocityRecordSObjectType": "OmniProcess"
    },
    "PropertySetConfig": {
        "HTMLTemplateId": "",
        "bundle": "VPLReadStatementLineItems131",
        "controlWidth": 12,
        "dataJSON": false,
        "dataRaptor Input Parameters": [
            {
                "element": "GetStatement:Statement|1:StatementID",
                "inputParam": "Id"
            }
        ],
        "enableActionMessage": false,
        "enableDefaultAbort": false,
        "errorMessage": {
            "custom": [
            ],
            "default": null
        },
        "failureAbortLabel": "Abort",
        "failureAbortMessage": "Are you sure?",
        "failureGoBackLabel": "Go Back",
        "failureNextLabel": "Continue",
        "ignoreCache": false,
        "inProgressMessage": "In Progress",
        "itemsKey": "recSet",
        "label": "Retrieve Statement Items",
        "maxCompareSize": 4,
        "message": {
        },
        "modalController": "ModalInstanceCtrl",
        "modalHTMLTemplateId": "vlcModalContent.html",
        "modalSize": "",
        "postMessage": "Done",
        "postTransformBundle": "",
        "preTransformBundle": "",
        "pubsub": false,
        "redirectNextLabel": "Next",
        "redirectNextWidth": 3,
        "redirectPageName": "",
        "redirectPreviousLabel": "Previous",
        "redirectPreviousWidth": 3,
        "redirectTemplateUrl": "vlcAcknowledge.html",
        "remoteClass": "",
        "remoteMethod": "",
        "remoteOptions": {
            "postTransformBundle": "",
            "preTransformBundle": ""
        },
        "remoteTimeout": 30000,
        "selectMode": "Single",
        "show": null,
        "showPersistentComponent": [
            true
        ],
        "ssm": false,
        "validationRequired": "None",
        "wpm": false
    },
    "Type": "DataRaptor Extract Action",
    "VlocityDataPackType": "SObject",
    "VlocityRecordSObjectType": "OmniProcessElement",
    "VlocityRecordSourceKey": "OmniProcessElement/OmniProcess/Service/BillingDispute/English/GetLineItems"
}