[
    {
        "CurrencyIsoCode": "USD",
        "GlobalKey": "f0c966d1-b98c-474b-a8b9-f983000f5f9f",
        "InputFieldName": "ProjectOpportunityId",
        "IsDisabled": false,
        "IsLocked": false,
        "IsRequiredForUpsert": true,
        "IsUpsertKey": true,
        "MayEdit": true,
        "Name": "VDOREGUpdateProjectInfoOnOppty",
        "OmniDataTransformationId": {
            "Name": "VDOREGUpdateProjectInfoOnOppty",
            "VlocityDataPackType": "VlocityMatchingKeyObject",
            "VlocityMatchingRecordSourceKey": "OmniDataTransform/VDOREGUpdateProjectInfoOnOppty",
            "VlocityRecordSObjectType": "OmniDataTransform"
        },
        "OutputCreationSequence": 1,
        "OutputFieldName": "Id",
        "OutputObjectName": "Opportunity",
        "VlocityDataPackType": "SObject",
        "VlocityRecordSObjectType": "OmniDataTransformItem"
    },
    {
        "CurrencyIsoCode": "USD",
        "FilterOperator": "=",
        "GlobalKey": "8b0ef92b-6d32-4e0e-9d32-4bde03edcdcc",
        "IsDisabled": true,
        "IsLocked": false,
        "IsRequiredForUpsert": false,
        "IsUpsertKey": false,
        "MayEdit": true,
        "MigrationValue": "FAKEMAPPING",
        "Name": "VDOREGUpdateProjectInfoOnOppty",
        "OmniDataTransformationId": {
            "Name": "VDOREGUpdateProjectInfoOnOppty",
            "VlocityDataPackType": "VlocityMatchingKeyObject",
            "VlocityMatchingRecordSourceKey": "OmniDataTransform/VDOREGUpdateProjectInfoOnOppty",
            "VlocityRecordSObjectType": "OmniDataTransform"
        },
        "OutputCreationSequence": 1,
        "OutputFieldName": "Id",
        "OutputObjectName": "Opportunity",
        "VlocityDataPackType": "SObject",
        "VlocityRecordSObjectType": "OmniDataTransformItem"
    },
    {
        "CurrencyIsoCode": "USD",
        "GlobalKey": "VDOREGUpdateProjectInfoOnOpptyCustom1529",
        "InputFieldName": "ProjectInfo:ProbabilityOfInfluence",
        "IsDisabled": false,
        "IsLocked": false,
        "IsRequiredForUpsert": false,
        "IsUpsertKey": false,
        "MayEdit": true,
        "Name": "VDOREGUpdateProjectInfoOnOppty",
        "OmniDataTransformationId": {
            "Name": "VDOREGUpdateProjectInfoOnOppty",
            "VlocityDataPackType": "VlocityMatchingKeyObject",
            "VlocityMatchingRecordSourceKey": "OmniDataTransform/VDOREGUpdateProjectInfoOnOppty",
            "VlocityRecordSObjectType": "OmniDataTransform"
        },
        "OutputCreationSequence": 1,
        "OutputFieldName": "ProbabilityOfInfluence__c",
        "OutputObjectName": "Opportunity",
        "VlocityDataPackType": "SObject",
        "VlocityRecordSObjectType": "OmniDataTransformItem"
    },
    {
        "CurrencyIsoCode": "USD",
        "GlobalKey": "VDOREGUpdateProjectInfoOnOpptyCustom1896",
        "InputFieldName": "ProjectInfo:ProjectDescription",
        "IsDisabled": false,
        "IsLocked": false,
        "IsRequiredForUpsert": false,
        "IsUpsertKey": false,
        "MayEdit": true,
        "Name": "VDOREGUpdateProjectInfoOnOppty",
        "OmniDataTransformationId": {
            "Name": "VDOREGUpdateProjectInfoOnOppty",
            "VlocityDataPackType": "VlocityMatchingKeyObject",
            "VlocityMatchingRecordSourceKey": "OmniDataTransform/VDOREGUpdateProjectInfoOnOppty",
            "VlocityRecordSObjectType": "OmniDataTransform"
        },
        "OutputCreationSequence": 1,
        "OutputFieldName": "ProjectDescription__c",
        "OutputObjectName": "Opportunity",
        "VlocityDataPackType": "SObject",
        "VlocityRecordSObjectType": "OmniDataTransformItem"
    },
    {
        "CurrencyIsoCode": "USD",
        "GlobalKey": "VDOREGUpdateProjectInfoOnOpptyCustom8538",
        "InputFieldName": "ProjectInfo:ProjectEndDate",
        "IsDisabled": false,
        "IsLocked": false,
        "IsRequiredForUpsert": false,
        "IsUpsertKey": false,
        "MayEdit": true,
        "Name": "VDOREGUpdateProjectInfoOnOppty",
        "OmniDataTransformationId": {
            "Name": "VDOREGUpdateProjectInfoOnOppty",
            "VlocityDataPackType": "VlocityMatchingKeyObject",
            "VlocityMatchingRecordSourceKey": "OmniDataTransform/VDOREGUpdateProjectInfoOnOppty",
            "VlocityRecordSObjectType": "OmniDataTransform"
        },
        "OutputCreationSequence": 1,
        "OutputFieldName": "ProjectEndDate__c",
        "OutputObjectName": "Opportunity",
        "VlocityDataPackType": "SObject",
        "VlocityRecordSObjectType": "OmniDataTransformItem"
    },
    {
        "CurrencyIsoCode": "USD",
        "GlobalKey": "VDOREGUpdateProjectInfoOnOpptyCustom9443",
        "InputFieldName": "ProjectInfo:ProjectGoals",
        "IsDisabled": false,
        "IsLocked": false,
        "IsRequiredForUpsert": false,
        "IsUpsertKey": false,
        "MayEdit": true,
        "Name": "VDOREGUpdateProjectInfoOnOppty",
        "OmniDataTransformationId": {
            "Name": "VDOREGUpdateProjectInfoOnOppty",
            "VlocityDataPackType": "VlocityMatchingKeyObject",
            "VlocityMatchingRecordSourceKey": "OmniDataTransform/VDOREGUpdateProjectInfoOnOppty",
            "VlocityRecordSObjectType": "OmniDataTransform"
        },
        "OutputCreationSequence": 1,
        "OutputFieldName": "ProjectGoals__c",
        "OutputObjectName": "Opportunity",
        "VlocityDataPackType": "SObject",
        "VlocityRecordSObjectType": "OmniDataTransformItem"
    },
    {
        "CurrencyIsoCode": "USD",
        "GlobalKey": "VDOREGUpdateProjectInfoOnOpptyCustom5628",
        "InputFieldName": "ProjectInfo:ProjectStage",
        "IsDisabled": false,
        "IsLocked": false,
        "IsRequiredForUpsert": false,
        "IsUpsertKey": false,
        "MayEdit": true,
        "Name": "VDOREGUpdateProjectInfoOnOppty",
        "OmniDataTransformationId": {
            "Name": "VDOREGUpdateProjectInfoOnOppty",
            "VlocityDataPackType": "VlocityMatchingKeyObject",
            "VlocityMatchingRecordSourceKey": "OmniDataTransform/VDOREGUpdateProjectInfoOnOppty",
            "VlocityRecordSObjectType": "OmniDataTransform"
        },
        "OutputCreationSequence": 1,
        "OutputFieldName": "ProjectStage__c",
        "OutputObjectName": "Opportunity",
        "VlocityDataPackType": "SObject",
        "VlocityRecordSObjectType": "OmniDataTransformItem"
    },
    {
        "CurrencyIsoCode": "USD",
        "GlobalKey": "VDOREGUpdateProjectInfoOnOpptyCustom3238",
        "InputFieldName": "ProjectInfo:ProjectStartDate",
        "IsDisabled": false,
        "IsLocked": false,
        "IsRequiredForUpsert": false,
        "IsUpsertKey": false,
        "MayEdit": true,
        "Name": "VDOREGUpdateProjectInfoOnOppty",
        "OmniDataTransformationId": {
            "Name": "VDOREGUpdateProjectInfoOnOppty",
            "VlocityDataPackType": "VlocityMatchingKeyObject",
            "VlocityMatchingRecordSourceKey": "OmniDataTransform/VDOREGUpdateProjectInfoOnOppty",
            "VlocityRecordSObjectType": "OmniDataTransform"
        },
        "OutputCreationSequence": 1,
        "OutputFieldName": "ProjectStartDate__c",
        "OutputObjectName": "Opportunity",
        "VlocityDataPackType": "SObject",
        "VlocityRecordSObjectType": "OmniDataTransformItem"
    }
]