[
    {
        "CurrencyIsoCode": "USD",
        "FilterGroup": 0,
        "FilterOperator": "=",
        "FilterValue": "OrderId",
        "GlobalKey": "GetOrderDetailswithOrderId12940831165884115",
        "InputFieldName": "Id",
        "InputObjectName": "Order",
        "InputObjectQuerySequence": 1,
        "IsDisabled": false,
        "IsLocked": false,
        "IsRequiredForUpsert": false,
        "IsUpsertKey": false,
        "MayEdit": true,
        "Name": "GetOrderDetailswithOrderId",
        "OmniDataTransformationId": {
            "Name": "GetOrderDetailswithOrderId",
            "VlocityDataPackType": "VlocityMatchingKeyObject",
            "VlocityMatchingRecordSourceKey": "OmniDataTransform/GetOrderDetailswithOrderId",
            "VlocityRecordSObjectType": "OmniDataTransform"
        },
        "OutputCreationSequence": 0,
        "OutputFieldName": "Order",
        "OutputObjectName": "json",
        "VlocityDataPackType": "SObject",
        "VlocityRecordSObjectType": "OmniDataTransformItem"
    },
    {
        "CurrencyIsoCode": "USD",
        "FilterGroup": 0,
        "FilterOperator": "=",
        "FilterValue": "Order:Id",
        "GlobalKey": "GetOrderDetailswithOrderId3091623302083135",
        "InputFieldName": "OrderId",
        "InputObjectName": "OrderItem",
        "InputObjectQuerySequence": 2,
        "IsDisabled": false,
        "IsLocked": false,
        "IsRequiredForUpsert": false,
        "IsUpsertKey": false,
        "MayEdit": true,
        "Name": "GetOrderDetailswithOrderId",
        "OmniDataTransformationId": {
            "Name": "GetOrderDetailswithOrderId",
            "VlocityDataPackType": "VlocityMatchingKeyObject",
            "VlocityMatchingRecordSourceKey": "OmniDataTransform/GetOrderDetailswithOrderId",
            "VlocityRecordSObjectType": "OmniDataTransform"
        },
        "OutputCreationSequence": 0,
        "OutputFieldName": "Order:OrderItem",
        "OutputObjectName": "json",
        "VlocityDataPackType": "SObject",
        "VlocityRecordSObjectType": "OmniDataTransformItem"
    },
    {
        "CurrencyIsoCode": "USD",
        "FormulaExpression": "IF( ISBLANK (Order:%vlocity_namespace%__OrchestrationPlanId__c),\"false\",\"true\")",
        "FormulaResultPath": "HasOrchestration",
        "FormulaSequence": 1,
        "GlobalKey": "GetOrderDetailswithOrderId7968356772675038",
        "IsDisabled": false,
        "IsLocked": false,
        "IsRequiredForUpsert": false,
        "IsUpsertKey": false,
        "MayEdit": true,
        "Name": "GetOrderDetailswithOrderId",
        "OmniDataTransformationId": {
            "Name": "GetOrderDetailswithOrderId",
            "VlocityDataPackType": "VlocityMatchingKeyObject",
            "VlocityMatchingRecordSourceKey": "OmniDataTransform/GetOrderDetailswithOrderId",
            "VlocityRecordSObjectType": "OmniDataTransform"
        },
        "OutputCreationSequence": 0,
        "OutputFieldName": "Formula",
        "OutputObjectName": "Formula",
        "VlocityDataPackType": "SObject",
        "VlocityRecordSObjectType": "OmniDataTransformItem"
    },
    {
        "CurrencyIsoCode": "USD",
        "FormulaExpression": "IF( ISBLANK (Order:QuoteId),\"false\",\"true\")",
        "FormulaResultPath": "HasQuote",
        "FormulaSequence": 2,
        "GlobalKey": "GetOrderDetailswithOrderId9656692091056549",
        "IsDisabled": false,
        "IsLocked": false,
        "IsRequiredForUpsert": false,
        "IsUpsertKey": false,
        "MayEdit": true,
        "Name": "GetOrderDetailswithOrderId",
        "OmniDataTransformationId": {
            "Name": "GetOrderDetailswithOrderId",
            "VlocityDataPackType": "VlocityMatchingKeyObject",
            "VlocityMatchingRecordSourceKey": "OmniDataTransform/GetOrderDetailswithOrderId",
            "VlocityRecordSObjectType": "OmniDataTransform"
        },
        "OutputCreationSequence": 0,
        "OutputFieldName": "Formula",
        "OutputObjectName": "Formula",
        "VlocityDataPackType": "SObject",
        "VlocityRecordSObjectType": "OmniDataTransformItem"
    },
    {
        "CurrencyIsoCode": "USD",
        "GlobalKey": "GetOrderDetailswithOrderId8578149020646546",
        "InputFieldName": "Order:AccountId",
        "IsDisabled": false,
        "IsLocked": false,
        "IsRequiredForUpsert": false,
        "IsUpsertKey": false,
        "MayEdit": true,
        "Name": "GetOrderDetailswithOrderId",
        "OmniDataTransformationId": {
            "Name": "GetOrderDetailswithOrderId",
            "VlocityDataPackType": "VlocityMatchingKeyObject",
            "VlocityMatchingRecordSourceKey": "OmniDataTransform/GetOrderDetailswithOrderId",
            "VlocityRecordSObjectType": "OmniDataTransform"
        },
        "OutputCreationSequence": 1,
        "OutputFieldName": "AccountId",
        "OutputObjectName": "json",
        "VlocityDataPackType": "SObject",
        "VlocityRecordSObjectType": "OmniDataTransformItem"
    },
    {
        "CurrencyIsoCode": "USD",
        "GlobalKey": "GetOrderDetailswithOrderId6799842163612653",
        "InputFieldName": "Order:Account.Name",
        "IsDisabled": false,
        "IsLocked": false,
        "IsRequiredForUpsert": false,
        "IsUpsertKey": false,
        "MayEdit": true,
        "Name": "GetOrderDetailswithOrderId",
        "OmniDataTransformationId": {
            "Name": "GetOrderDetailswithOrderId",
            "VlocityDataPackType": "VlocityMatchingKeyObject",
            "VlocityMatchingRecordSourceKey": "OmniDataTransform/GetOrderDetailswithOrderId",
            "VlocityRecordSObjectType": "OmniDataTransform"
        },
        "OutputCreationSequence": 1,
        "OutputFieldName": "AccountName",
        "OutputObjectName": "json",
        "VlocityDataPackType": "SObject",
        "VlocityRecordSObjectType": "OmniDataTransformItem"
    },
    {
        "CurrencyIsoCode": "USD",
        "GlobalKey": "GetOrderDetailswithOrderId526297130007126",
        "InputFieldName": "HasOrchestration",
        "IsDisabled": false,
        "IsLocked": false,
        "IsRequiredForUpsert": false,
        "IsUpsertKey": false,
        "MayEdit": true,
        "Name": "GetOrderDetailswithOrderId",
        "OmniDataTransformationId": {
            "Name": "GetOrderDetailswithOrderId",
            "VlocityDataPackType": "VlocityMatchingKeyObject",
            "VlocityMatchingRecordSourceKey": "OmniDataTransform/GetOrderDetailswithOrderId",
            "VlocityRecordSObjectType": "OmniDataTransform"
        },
        "OutputCreationSequence": 1,
        "OutputFieldName": "HasOrchestration",
        "OutputObjectName": "json",
        "VlocityDataPackType": "SObject",
        "VlocityRecordSObjectType": "OmniDataTransformItem"
    },
    {
        "CurrencyIsoCode": "USD",
        "GlobalKey": "GetOrderDetailswithOrderId6769725081254723",
        "InputFieldName": "HasQuote",
        "IsDisabled": false,
        "IsLocked": false,
        "IsRequiredForUpsert": false,
        "IsUpsertKey": false,
        "MayEdit": true,
        "Name": "GetOrderDetailswithOrderId",
        "OmniDataTransformationId": {
            "Name": "GetOrderDetailswithOrderId",
            "VlocityDataPackType": "VlocityMatchingKeyObject",
            "VlocityMatchingRecordSourceKey": "OmniDataTransform/GetOrderDetailswithOrderId",
            "VlocityRecordSObjectType": "OmniDataTransform"
        },
        "OutputCreationSequence": 1,
        "OutputFieldName": "HasQuote",
        "OutputObjectName": "json",
        "VlocityDataPackType": "SObject",
        "VlocityRecordSObjectType": "OmniDataTransformItem"
    },
    {
        "CurrencyIsoCode": "USD",
        "GlobalKey": "GetOrderDetailswithOrderId650752290175854",
        "InputFieldName": "Order:%vlocity_namespace%__OrchestrationPlanId__r.Name",
        "IsDisabled": false,
        "IsLocked": false,
        "IsRequiredForUpsert": false,
        "IsUpsertKey": false,
        "MayEdit": true,
        "Name": "GetOrderDetailswithOrderId",
        "OmniDataTransformationId": {
            "Name": "GetOrderDetailswithOrderId",
            "VlocityDataPackType": "VlocityMatchingKeyObject",
            "VlocityMatchingRecordSourceKey": "OmniDataTransform/GetOrderDetailswithOrderId",
            "VlocityRecordSObjectType": "OmniDataTransform"
        },
        "OutputCreationSequence": 1,
        "OutputFieldName": "OMName",
        "OutputObjectName": "json",
        "VlocityDataPackType": "SObject",
        "VlocityRecordSObjectType": "OmniDataTransformItem"
    },
    {
        "CurrencyIsoCode": "USD",
        "GlobalKey": "GetOrderDetailswithOrderId028373732659959572",
        "InputFieldName": "Order:%vlocity_namespace%__OrchestrationPlanId__c",
        "IsDisabled": false,
        "IsLocked": false,
        "IsRequiredForUpsert": false,
        "IsUpsertKey": false,
        "MayEdit": true,
        "Name": "GetOrderDetailswithOrderId",
        "OmniDataTransformationId": {
            "Name": "GetOrderDetailswithOrderId",
            "VlocityDataPackType": "VlocityMatchingKeyObject",
            "VlocityMatchingRecordSourceKey": "OmniDataTransform/GetOrderDetailswithOrderId",
            "VlocityRecordSObjectType": "OmniDataTransform"
        },
        "OutputCreationSequence": 1,
        "OutputFieldName": "OMPlanId",
        "OutputObjectName": "json",
        "VlocityDataPackType": "SObject",
        "VlocityRecordSObjectType": "OmniDataTransformItem"
    },
    {
        "CurrencyIsoCode": "USD",
        "GlobalKey": "GetOrderDetailswithOrderId955106417338768",
        "InputFieldName": "Order:%vlocity_namespace%__OrchestrationPlanId__r.%vlocity_namespace%__State__c",
        "IsDisabled": false,
        "IsLocked": false,
        "IsRequiredForUpsert": false,
        "IsUpsertKey": false,
        "MayEdit": true,
        "Name": "GetOrderDetailswithOrderId",
        "OmniDataTransformationId": {
            "Name": "GetOrderDetailswithOrderId",
            "VlocityDataPackType": "VlocityMatchingKeyObject",
            "VlocityMatchingRecordSourceKey": "OmniDataTransform/GetOrderDetailswithOrderId",
            "VlocityRecordSObjectType": "OmniDataTransform"
        },
        "OutputCreationSequence": 1,
        "OutputFieldName": "OMState",
        "OutputObjectName": "json",
        "VlocityDataPackType": "SObject",
        "VlocityRecordSObjectType": "OmniDataTransformItem"
    },
    {
        "CurrencyIsoCode": "USD",
        "GlobalKey": "GetOrderDetailswithOrderId3475916459042867",
        "InputFieldName": "Order:%vlocity_namespace%__EffectiveOneTimeTotal__c",
        "IsDisabled": false,
        "IsLocked": false,
        "IsRequiredForUpsert": false,
        "IsUpsertKey": false,
        "MayEdit": true,
        "Name": "GetOrderDetailswithOrderId",
        "OmniDataTransformationId": {
            "Name": "GetOrderDetailswithOrderId",
            "VlocityDataPackType": "VlocityMatchingKeyObject",
            "VlocityMatchingRecordSourceKey": "OmniDataTransform/GetOrderDetailswithOrderId",
            "VlocityRecordSObjectType": "OmniDataTransform"
        },
        "OutputCreationSequence": 1,
        "OutputFieldFormat": "Currency",
        "OutputFieldName": "OneTimeTotal",
        "OutputObjectName": "json",
        "VlocityDataPackType": "SObject",
        "VlocityRecordSObjectType": "OmniDataTransformItem"
    },
    {
        "CurrencyIsoCode": "USD",
        "GlobalKey": "GetOrderDetailswithOrderId060614401400232776",
        "InputFieldName": "Order:OpportunityId",
        "IsDisabled": false,
        "IsLocked": false,
        "IsRequiredForUpsert": false,
        "IsUpsertKey": false,
        "MayEdit": true,
        "Name": "GetOrderDetailswithOrderId",
        "OmniDataTransformationId": {
            "Name": "GetOrderDetailswithOrderId",
            "VlocityDataPackType": "VlocityMatchingKeyObject",
            "VlocityMatchingRecordSourceKey": "OmniDataTransform/GetOrderDetailswithOrderId",
            "VlocityRecordSObjectType": "OmniDataTransform"
        },
        "OutputCreationSequence": 1,
        "OutputFieldName": "OpportunityId",
        "OutputObjectName": "json",
        "VlocityDataPackType": "SObject",
        "VlocityRecordSObjectType": "OmniDataTransformItem"
    },
    {
        "CurrencyIsoCode": "USD",
        "GlobalKey": "GetOrderDetailswithOrderId5252063124135882",
        "InputFieldName": "Order:Id",
        "IsDisabled": false,
        "IsLocked": false,
        "IsRequiredForUpsert": false,
        "IsUpsertKey": false,
        "MayEdit": true,
        "Name": "GetOrderDetailswithOrderId",
        "OmniDataTransformationId": {
            "Name": "GetOrderDetailswithOrderId",
            "VlocityDataPackType": "VlocityMatchingKeyObject",
            "VlocityMatchingRecordSourceKey": "OmniDataTransform/GetOrderDetailswithOrderId",
            "VlocityRecordSObjectType": "OmniDataTransform"
        },
        "OutputCreationSequence": 1,
        "OutputFieldName": "OrderId",
        "OutputObjectName": "json",
        "VlocityDataPackType": "SObject",
        "VlocityRecordSObjectType": "OmniDataTransformItem"
    },
    {
        "CurrencyIsoCode": "USD",
        "GlobalKey": "GetOrderDetailswithOrderId749597623839303",
        "InputFieldName": "Order:OrderItem:%vlocity_namespace%__LineNumber__c",
        "IsDisabled": false,
        "IsLocked": false,
        "IsRequiredForUpsert": false,
        "IsUpsertKey": false,
        "MayEdit": true,
        "Name": "GetOrderDetailswithOrderId",
        "OmniDataTransformationId": {
            "Name": "GetOrderDetailswithOrderId",
            "VlocityDataPackType": "VlocityMatchingKeyObject",
            "VlocityMatchingRecordSourceKey": "OmniDataTransform/GetOrderDetailswithOrderId",
            "VlocityRecordSObjectType": "OmniDataTransform"
        },
        "OutputCreationSequence": 1,
        "OutputFieldName": "OrderItem:LineNumber",
        "OutputObjectName": "json",
        "VlocityDataPackType": "SObject",
        "VlocityRecordSObjectType": "OmniDataTransformItem"
    },
    {
        "CurrencyIsoCode": "USD",
        "GlobalKey": "GetOrderDetailswithOrderId2775488403578885",
        "InputFieldName": "Order:OrderItem:Id",
        "IsDisabled": false,
        "IsLocked": false,
        "IsRequiredForUpsert": false,
        "IsUpsertKey": false,
        "MayEdit": true,
        "Name": "GetOrderDetailswithOrderId",
        "OmniDataTransformationId": {
            "Name": "GetOrderDetailswithOrderId",
            "VlocityDataPackType": "VlocityMatchingKeyObject",
            "VlocityMatchingRecordSourceKey": "OmniDataTransform/GetOrderDetailswithOrderId",
            "VlocityRecordSObjectType": "OmniDataTransform"
        },
        "OutputCreationSequence": 1,
        "OutputFieldName": "OrderItem:OrderItemId",
        "OutputObjectName": "json",
        "VlocityDataPackType": "SObject",
        "VlocityRecordSObjectType": "OmniDataTransformItem"
    },
    {
        "CurrencyIsoCode": "USD",
        "GlobalKey": "GetOrderDetailswithOrderId6107247309529344",
        "InputFieldName": "Order:OrderItem:ProductName__c",
        "IsDisabled": false,
        "IsLocked": false,
        "IsRequiredForUpsert": false,
        "IsUpsertKey": false,
        "MayEdit": true,
        "Name": "GetOrderDetailswithOrderId",
        "OmniDataTransformationId": {
            "Name": "GetOrderDetailswithOrderId",
            "VlocityDataPackType": "VlocityMatchingKeyObject",
            "VlocityMatchingRecordSourceKey": "OmniDataTransform/GetOrderDetailswithOrderId",
            "VlocityRecordSObjectType": "OmniDataTransform"
        },
        "OutputCreationSequence": 1,
        "OutputFieldName": "OrderItem:ProductName",
        "OutputObjectName": "json",
        "VlocityDataPackType": "SObject",
        "VlocityRecordSObjectType": "OmniDataTransformItem"
    },
    {
        "CurrencyIsoCode": "USD",
        "GlobalKey": "GetOrderDetailswithOrderId7362602237533702",
        "InputFieldName": "Order:OrderItem:Quantity",
        "IsDisabled": false,
        "IsLocked": false,
        "IsRequiredForUpsert": false,
        "IsUpsertKey": false,
        "MayEdit": true,
        "Name": "GetOrderDetailswithOrderId",
        "OmniDataTransformationId": {
            "Name": "GetOrderDetailswithOrderId",
            "VlocityDataPackType": "VlocityMatchingKeyObject",
            "VlocityMatchingRecordSourceKey": "OmniDataTransform/GetOrderDetailswithOrderId",
            "VlocityRecordSObjectType": "OmniDataTransform"
        },
        "OutputCreationSequence": 1,
        "OutputFieldFormat": "Number",
        "OutputFieldName": "OrderItem:Quantity",
        "OutputObjectName": "json",
        "VlocityDataPackType": "SObject",
        "VlocityRecordSObjectType": "OmniDataTransformItem"
    },
    {
        "CurrencyIsoCode": "USD",
        "GlobalKey": "GetOrderDetailswithOrderId9265497512145104",
        "InputFieldName": "Order:Name",
        "IsDisabled": false,
        "IsLocked": false,
        "IsRequiredForUpsert": false,
        "IsUpsertKey": false,
        "MayEdit": true,
        "Name": "GetOrderDetailswithOrderId",
        "OmniDataTransformationId": {
            "Name": "GetOrderDetailswithOrderId",
            "VlocityDataPackType": "VlocityMatchingKeyObject",
            "VlocityMatchingRecordSourceKey": "OmniDataTransform/GetOrderDetailswithOrderId",
            "VlocityRecordSObjectType": "OmniDataTransform"
        },
        "OutputCreationSequence": 1,
        "OutputFieldName": "OrderName",
        "OutputObjectName": "json",
        "VlocityDataPackType": "SObject",
        "VlocityRecordSObjectType": "OmniDataTransformItem"
    },
    {
        "CurrencyIsoCode": "USD",
        "GlobalKey": "GetOrderDetailswithOrderId43159527182302715",
        "InputFieldName": "Order:OrderNumber",
        "IsDisabled": false,
        "IsLocked": false,
        "IsRequiredForUpsert": false,
        "IsUpsertKey": false,
        "MayEdit": true,
        "Name": "GetOrderDetailswithOrderId",
        "OmniDataTransformationId": {
            "Name": "GetOrderDetailswithOrderId",
            "VlocityDataPackType": "VlocityMatchingKeyObject",
            "VlocityMatchingRecordSourceKey": "OmniDataTransform/GetOrderDetailswithOrderId",
            "VlocityRecordSObjectType": "OmniDataTransform"
        },
        "OutputCreationSequence": 1,
        "OutputFieldName": "OrderNumber",
        "OutputObjectName": "json",
        "VlocityDataPackType": "SObject",
        "VlocityRecordSObjectType": "OmniDataTransformItem"
    },
    {
        "CurrencyIsoCode": "USD",
        "GlobalKey": "GetOrderDetailswithOrderId15492704197117835",
        "InputFieldName": "Order:Status",
        "IsDisabled": false,
        "IsLocked": false,
        "IsRequiredForUpsert": false,
        "IsUpsertKey": false,
        "MayEdit": true,
        "Name": "GetOrderDetailswithOrderId",
        "OmniDataTransformationId": {
            "Name": "GetOrderDetailswithOrderId",
            "VlocityDataPackType": "VlocityMatchingKeyObject",
            "VlocityMatchingRecordSourceKey": "OmniDataTransform/GetOrderDetailswithOrderId",
            "VlocityRecordSObjectType": "OmniDataTransform"
        },
        "OutputCreationSequence": 1,
        "OutputFieldName": "OrderStatus",
        "OutputObjectName": "json",
        "VlocityDataPackType": "SObject",
        "VlocityRecordSObjectType": "OmniDataTransformItem"
    },
    {
        "CurrencyIsoCode": "USD",
        "GlobalKey": "GetOrderDetailswithOrderId40016342380053427",
        "InputFieldName": "Order:%vlocity_namespace%__EffectiveOrderTotal__c",
        "IsDisabled": false,
        "IsLocked": false,
        "IsRequiredForUpsert": false,
        "IsUpsertKey": false,
        "MayEdit": true,
        "Name": "GetOrderDetailswithOrderId",
        "OmniDataTransformationId": {
            "Name": "GetOrderDetailswithOrderId",
            "VlocityDataPackType": "VlocityMatchingKeyObject",
            "VlocityMatchingRecordSourceKey": "OmniDataTransform/GetOrderDetailswithOrderId",
            "VlocityRecordSObjectType": "OmniDataTransform"
        },
        "OutputCreationSequence": 1,
        "OutputFieldFormat": "Currency",
        "OutputFieldName": "OrderTotal",
        "OutputObjectName": "json",
        "VlocityDataPackType": "SObject",
        "VlocityRecordSObjectType": "OmniDataTransformItem"
    },
    {
        "CurrencyIsoCode": "USD",
        "GlobalKey": "GetOrderDetailswithOrderId4397032341971625",
        "InputFieldName": "Order:QuoteId",
        "IsDisabled": false,
        "IsLocked": false,
        "IsRequiredForUpsert": false,
        "IsUpsertKey": false,
        "MayEdit": true,
        "Name": "GetOrderDetailswithOrderId",
        "OmniDataTransformationId": {
            "Name": "GetOrderDetailswithOrderId",
            "VlocityDataPackType": "VlocityMatchingKeyObject",
            "VlocityMatchingRecordSourceKey": "OmniDataTransform/GetOrderDetailswithOrderId",
            "VlocityRecordSObjectType": "OmniDataTransform"
        },
        "OutputCreationSequence": 1,
        "OutputFieldName": "QuoteId",
        "OutputObjectName": "json",
        "VlocityDataPackType": "SObject",
        "VlocityRecordSObjectType": "OmniDataTransformItem"
    },
    {
        "CurrencyIsoCode": "USD",
        "GlobalKey": "GetOrderDetailswithOrderId4994061297399237",
        "InputFieldName": "Order:%vlocity_namespace%__EffectiveRecurringTotal__c",
        "IsDisabled": false,
        "IsLocked": false,
        "IsRequiredForUpsert": false,
        "IsUpsertKey": false,
        "MayEdit": true,
        "Name": "GetOrderDetailswithOrderId",
        "OmniDataTransformationId": {
            "Name": "GetOrderDetailswithOrderId",
            "VlocityDataPackType": "VlocityMatchingKeyObject",
            "VlocityMatchingRecordSourceKey": "OmniDataTransform/GetOrderDetailswithOrderId",
            "VlocityRecordSObjectType": "OmniDataTransform"
        },
        "OutputCreationSequence": 1,
        "OutputFieldFormat": "Currency",
        "OutputFieldName": "RecurringTotal",
        "OutputObjectName": "json",
        "VlocityDataPackType": "SObject",
        "VlocityRecordSObjectType": "OmniDataTransformItem"
    },
    {
        "CurrencyIsoCode": "USD",
        "GlobalKey": "GetOrderDetailswithOrderId5678874128127005",
        "InputFieldName": "Order:EffectiveDate",
        "IsDisabled": false,
        "IsLocked": false,
        "IsRequiredForUpsert": false,
        "IsUpsertKey": false,
        "MayEdit": true,
        "Name": "GetOrderDetailswithOrderId",
        "OmniDataTransformationId": {
            "Name": "GetOrderDetailswithOrderId",
            "VlocityDataPackType": "VlocityMatchingKeyObject",
            "VlocityMatchingRecordSourceKey": "OmniDataTransform/GetOrderDetailswithOrderId",
            "VlocityRecordSObjectType": "OmniDataTransform"
        },
        "OutputCreationSequence": 1,
        "OutputFieldFormat": "Date(MM/dd/yyyy)",
        "OutputFieldName": "StartDate",
        "OutputObjectName": "json",
        "VlocityDataPackType": "SObject",
        "VlocityRecordSObjectType": "OmniDataTransformItem"
    }
]